tktable/Table.py
tktable/__init__.py
tktable-0.2.dist-info/METADATA
tktable-0.2.dist-info/WHEEL
tktable-0.2.dist-info/top_level.txt
tktable-0.2.dist-info/RECORD
