Metadata-Version: 2.1
Name: tktable
Version: 0.2
Summary: A Simple Solution to easily use tables in any Tkinter Application
Home-page: UNKNOWN
Author: Nitin Garg
License: UNKNOWN
Platform: UNKNOWN
Requires-Dist: ttkbootstrap (>=1.10.1)
